{
    "flowSegmentData": {
        "frc": "FRC2",
        "currentSpeed": 42,
        "freeFlowSpeed": 42,
        "currentTravelTime": 812,
        "freeFlowTravelTime": 812,
        "confidence": 1,
        "roadClosure": false,
        "coordinates": {
            "coordinate": [
                {
                    "latitude": 10.858115927097085,
                    "longitude": 106.78786439979166
                },
                {
                    "latitude": 10.858070322703913,
                    "longitude": 106.78789122188186
                },
                {
                    "latitude": 10.858016651098694,
                    "longitude": 106.78792206728554
                },
                {
                    "latitude": 10.857787311891656,
                    "longitude": 106.78805349552727
                },
                {
                    "latitude": 10.85771890522405,
                    "longitude": 106.78809372866249
                },
                {
                    "latitude": 10.85761971141222,
                    "longitude": 106.78808836424446
                },
                {
                    "latitude": 10.857501666617345,
                    "longitude": 106.78808568203544
                },
                {
                    "latitude": 10.855999596036257,
                    "longitude": 106.78902311408638
                },
                {
                    "latitude": 10.855603970775164,
                    "longitude": 106.78926048958425
                },
                {
                    "latitude": 10.855405499394982,
                    "longitude": 106.7894576319469
                },
                {
                    "latitude": 10.855317006306638,
                    "longitude": 106.78959844792018
                },
                {
                    "latitude": 10.855279468765398,
                    "longitude": 106.78965745651857
                },
                {
                    "latitude": 10.855156072297284,
                    "longitude": 106.78997261607788
                },
                {
                    "latitude": 10.854977686519176,
                    "longitude": 106.79068206036249
                },
                {
                    "latitude": 10.85452846999245,
                    "longitude": 106.7922980912943
                },
                {
                    "latitude": 10.854437260103904,
                    "longitude": 106.79264141404826
                },
                {
                    "latitude": 10.854254840243325,
                    "longitude": 106.79332537734723
                },
                {
                    "latitude": 10.854095222773946,
                    "longitude": 106.79392753327124
                },
                {
                    "latitude": 10.854016113723214,
                    "longitude": 106.79421855294942
                },
                {
                    "latitude": 10.853750633145022,
                    "longitude": 106.7952015825536
                },
                {
                    "latitude": 10.853591015406327,
                    "longitude": 106.79580507958212
                },
                {
                    "latitude": 10.853456916683212,
                    "longitude": 106.79607732379719
                },
                {
                    "latitude": 10.853207487958992,
                    "longitude": 106.7964474686413
                },
                {
                    "latitude": 10.852629438148302,
                    "longitude": 106.79709119880505
                },
                {
                    "latitude": 10.852437632709185,
                    "longitude": 106.79729236448117
                },
                {
                    "latitude": 10.85209699253147,
                    "longitude": 106.79765312159378
                },
                {
                    "latitude": 10.851855630043882,
                    "longitude": 106.79790793145025
                },
                {
                    "latitude": 10.851419744702948,
                    "longitude": 106.79836658919191
                },
                {
                    "latitude": 10.851048233239204,
                    "longitude": 106.7987568506037
                },
                {
                    "latitude": 10.849096987850782,
                    "longitude": 106.80080605829153
                },
                {
                    "latitude": 10.848694603131397,
                    "longitude": 106.80120838964388
                },
                {
                    "latitude": 10.848288266457645,
                    "longitude": 106.80161474430969
                },
                {
                    "latitude": 10.847954371889397,
                    "longitude": 106.80196611369075
                },
                {
                    "latitude": 10.847517163719118,
                    "longitude": 106.80242477143241
                },
                {
                    "latitude": 10.847423235086946,
                    "longitude": 106.80251864874793
                },
                {
                    "latitude": 10.84713494562154,
                    "longitude": 106.80281369173963
                },
                {
                    "latitude": 10.846528730087954,
                    "longitude": 106.80343998754478
                },
                {
                    "latitude": 10.846125107086879,
                    "longitude": 106.80387986982333
                },
                {
                    "latitude": 10.84561141926522,
                    "longitude": 106.80444045150756
                },
                {
                    "latitude": 10.845484067356239,
                    "longitude": 106.80457724416738
                },
                {
                    "latitude": 10.845277521708,
                    "longitude": 106.80480389082913
                },
                {
                    "latitude": 10.845072293068831,
                    "longitude": 106.80501846755038
                },
                {
                    "latitude": 10.844876531323496,
                    "longitude": 106.80522231543563
                },
                {
                    "latitude": 10.844671302409184,
                    "longitude": 106.80542750442527
                },
                {
                    "latitude": 10.84458412329706,
                    "longitude": 106.80551467621825
                },
                {
                    "latitude": 10.84448624228065,
                    "longitude": 106.80561257684735
                },
                {
                    "latitude": 10.844369591776026,
                    "longitude": 106.8057292529395
                },
                {
                    "latitude": 10.843872036113487,
                    "longitude": 106.80624691927949
                },
                {
                    "latitude": 10.84313039345147,
                    "longitude": 106.807019395476
                },
                {
                    "latitude": 10.842656956265094,
                    "longitude": 106.80751426303937
                },
                {
                    "latitude": 10.841530450999453,
                    "longitude": 106.80868772948367
                },
                {
                    "latitude": 10.83967035793295,
                    "longitude": 106.81060148561619
                },
                {
                    "latitude": 10.839375310464119,
                    "longitude": 106.8108884819809
                },
                {
                    "latitude": 10.839211651195807,
                    "longitude": 106.81099040592346
                },
                {
                    "latitude": 10.839035972585851,
                    "longitude": 106.81109903538857
                },
                {
                    "latitude": 10.838999750179225,
                    "longitude": 106.81109769428406
                },
                {
                    "latitude": 10.838962210589532,
                    "longitude": 106.81109903538857
                },
                {
                    "latitude": 10.838924670995153,
                    "longitude": 106.8111043998066
                },
                {
                    "latitude": 10.838718120818072,
                    "longitude": 106.81096760714684
                },
                {
                    "latitude": 10.838476747532935,
                    "longitude": 106.81080667460589
                },
                {
                    "latitude": 10.838079781904636,
                    "longitude": 106.81046066964291
                },
                {
                    "latitude": 10.837354260410835,
                    "longitude": 106.80978207076197
                },
                {
                    "latitude": 10.837181215083596,
                    "longitude": 106.80961979711651
                },
                {
                    "latitude": 10.836973346515824,
                    "longitude": 106.80942533696287
                },
                {
                    "latitude": 10.83680573436953,
                    "longitude": 106.8092684277355
                },
                {
                    "latitude": 10.836225018476602,
                    "longitude": 106.80882183993441
                },
                {
                    "latitude": 10.834928159084482,
                    "longitude": 106.80783076370318
                },
                {
                    "latitude": 10.834505750359186,
                    "longitude": 106.80753974402501
                },
                {
                    "latitude": 10.83403905018001,
                    "longitude": 106.8072178789431
                },
                {
                    "latitude": 10.833326937903118,
                    "longitude": 106.80674849236539
                },
                {
                    "latitude": 10.833113715516177,
                    "longitude": 106.80661169970563
                },
                {
                    "latitude": 10.832739546906394,
                    "longitude": 106.80637164199874
                },
                {
                    "latitude": 10.832405552661074,
                    "longitude": 106.806158406382
                },
                {
                    "latitude": 10.8321601403346,
                    "longitude": 106.80600149715457
                },
                {
                    "latitude": 10.831508368345517,
                    "longitude": 106.8055857547572
                },
                {
                    "latitude": 10.831057799359542,
                    "longitude": 106.80529741728805
                },
                {
                    "latitude": 10.830798966805244,
                    "longitude": 106.80507077062623
                },
                {
                    "latitude": 10.8306608238937,
                    "longitude": 106.80495141232501
                },
                {
                    "latitude": 10.8305723234848,
                    "longitude": 106.80487362826352
                },
                {
                    "latitude": 10.830450234040555,
                    "longitude": 106.80476768100743
                },
                {
                    "latitude": 10.830333578065249,
                    "longitude": 106.80466709816938
                },
                {
                    "latitude": 10.830084130061534,
                    "longitude": 106.8044109472084
                },
                {
                    "latitude": 10.829731444806646,
                    "longitude": 106.80395631278026
                },
                {
                    "latitude": 10.829464543130875,
                    "longitude": 106.80362505996686
                },
                {
                    "latitude": 10.829051511907236,
                    "longitude": 106.80302156293834
                },
                {
                    "latitude": 10.828877144558296,
                    "longitude": 106.80277077639539
                },
                {
                    "latitude": 10.828494902654052,
                    "longitude": 106.8022155591292
                },
                {
                    "latitude": 10.828245453119015,
                    "longitude": 106.80186284864362
                },
                {
                    "latitude": 10.828165020006844,
                    "longitude": 106.80174885476049
                },
                {
                    "latitude": 10.828038977901247,
                    "longitude": 106.80157719338348
                },
                {
                    "latitude": 10.827770757489514,
                    "longitude": 106.80121107185289
                },
                {
                    "latitude": 10.827129678448403,
                    "longitude": 106.80032728398226
                },
                {
                    "latitude": 10.826507368612795,
                    "longitude": 106.79947031820183
                },
                {
                    "latitude": 10.825811374575924,
                    "longitude": 106.79859189474922
                },
                {
                    "latitude": 10.825712087856939,
                    "longitude": 106.79843230331278
                },
                {
                    "latitude": 10.825623585985962,
                    "longitude": 106.79831160390711
                },
                {
                    "latitude": 10.825225286079432,
                    "longitude": 106.7977188357147
                },
                {
                    "latitude": 10.824987935966075,
                    "longitude": 106.79736612522913
                },
                {
                    "latitude": 10.82325386663445,
                    "longitude": 106.79495616042868
                },
                {
                    "latitude": 10.822899856089776,
                    "longitude": 106.79448275053744
                },
                {
                    "latitude": 10.82218500049879,
                    "longitude": 106.79353593075496
                },
                {
                    "latitude": 10.82160837268055,
                    "longitude": 106.79277686560357
                },
                {
                    "latitude": 10.821523821363801,
                    "longitude": 106.7926668950339
                },
                {
                    "latitude": 10.821415230105076,
                    "longitude": 106.7925233968516
                },
                {
                    "latitude": 10.82090965042115,
                    "longitude": 106.79184345686622
                },
                {
                    "latitude": 10.820469768234014,
                    "longitude": 106.79125202977826
                },
                {
                    "latitude": 10.820402670295488,
                    "longitude": 106.79116217577626
                },
                {
                    "latitude": 10.82031013274576,
                    "longitude": 106.7910696395652
                },
                {
                    "latitude": 10.820212243794224,
                    "longitude": 106.79098917329475
                },
                {
                    "latitude": 10.820130408935514,
                    "longitude": 106.79093821132341
                },
                {
                    "latitude": 10.820023134433956,
                    "longitude": 106.79088724935212
                },
                {
                    "latitude": 10.819891737524808,
                    "longitude": 106.7908470162169
                },
                {
                    "latitude": 10.819793848436648,
                    "longitude": 106.79083360517183
                },
                {
                    "latitude": 10.819690525604939,
                    "longitude": 106.79083092296281
                },
                {
                    "latitude": 10.819585967802743,
                    "longitude": 106.79083092296281
                },
                {
                    "latitude": 10.819463956211122,
                    "longitude": 106.79086042726198
                },
                {
                    "latitude": 10.819367384248107,
                    "longitude": 106.79089529597917
                },
                {
                    "latitude": 10.819261426738857,
                    "longitude": 106.79093552911439
                },
                {
                    "latitude": 10.819138015420135,
                    "longitude": 106.79097576224967
                },
                {
                    "latitude": 10.81903205782979,
                    "longitude": 106.7910159953849
                },
                {
                    "latitude": 10.8189087287459,
                    "longitude": 106.79105622852012
                },
                {
                    "latitude": 10.818818825269576,
                    "longitude": 106.79107768619224
                },
                {
                    "latitude": 10.81857340181462,
                    "longitude": 106.79114474141767
                },
                {
                    "latitude": 10.818286401840279,
                    "longitude": 106.79119838559797
                },
                {
                    "latitude": 10.817660121825941,
                    "longitude": 106.79130030954053
                },
                {
                    "latitude": 10.817088836733648,
                    "longitude": 106.79138345802005
                },
                {
                    "latitude": 10.816518867830272,
                    "longitude": 106.79145990097697
                },
                {
                    "latitude": 10.816253353996137,
                    "longitude": 106.79149611079868
                },
                {
                    "latitude": 10.81616081516579,
                    "longitude": 106.79151086294826
                },
                {
                    "latitude": 10.81604678818706,
                    "longitude": 106.79152829730685
                },
                {
                    "latitude": 10.815928809325147,
                    "longitude": 106.79154707276996
                },
                {
                    "latitude": 10.815449977682672,
                    "longitude": 106.79162217462238
                },
                {
                    "latitude": 10.815010087485943,
                    "longitude": 106.7916878887433
                },
                {
                    "latitude": 10.814406606155131,
                    "longitude": 106.7917777427453
                },
                {
                    "latitude": 10.813800406700976,
                    "longitude": 106.79186491453834
                },
                {
                    "latitude": 10.813167448527679,
                    "longitude": 106.79192258203216
                },
                {
                    "latitude": 10.813026580573547,
                    "longitude": 106.7919292875547
                },
                {
                    "latitude": 10.812869740371502,
                    "longitude": 106.79192124092765
                },
                {
                    "latitude": 10.812649752296313,
                    "longitude": 106.79192258203216
                },
                {
                    "latitude": 10.812343975190347,
                    "longitude": 106.79190648877807
                },
                {
                    "latitude": 10.812160294716513,
                    "longitude": 106.79190648877807
                },
                {
                    "latitude": 10.81207442343892,
                    "longitude": 106.79191051209159
                },
                {
                    "latitude": 10.811473653132515,
                    "longitude": 106.79192392313666
                },
                {
                    "latitude": 10.810336327512259,
                    "longitude": 106.7919292875547
                },
                {
                    "latitude": 10.809377492964826,
                    "longitude": 106.79194403970428
                },
                {
                    "latitude": 10.808520500091717,
                    "longitude": 106.79195745074935
                },
                {
                    "latitude": 10.807722536999423,
                    "longitude": 106.79196817958541
                },
                {
                    "latitude": 10.806043448425658,
                    "longitude": 106.79199366057105
                },
                {
                    "latitude": 10.804898198257046,
                    "longitude": 106.792075467946
                },
                {
                    "latitude": 10.80486328905318,
                    "longitude": 106.79204059922881
                },
                {
                    "latitude": 10.804825745187864,
                    "longitude": 106.79201377713866
                },
                {
                    "latitude": 10.804757408754337,
                    "longitude": 106.79198829615302
                },
                {
                    "latitude": 10.80466618370794,
                    "longitude": 106.7919842728395
                },
                {
                    "latitude": 10.804596447575259,
                    "longitude": 106.7920030483026
                },
                {
                    "latitude": 10.804544166048395,
                    "longitude": 106.79203523481078
                },
                {
                    "latitude": 10.804502587819778,
                    "longitude": 106.792075467946
                },
                {
                    "latitude": 10.804066715904042,
                    "longitude": 106.79208351457305
                },
                {
                    "latitude": 10.800082254107615,
                    "longitude": 106.79215191090293
                },
                {
                    "latitude": 10.799909269601688,
                    "longitude": 106.7921452053804
                },
                {
                    "latitude": 10.799760408985666,
                    "longitude": 106.7921452053804
                },
                {
                    "latitude": 10.799044263243125,
                    "longitude": 106.79213045323081
                },
                {
                    "latitude": 10.798691541488713,
                    "longitude": 106.79213447654433
                },
                {
                    "latitude": 10.797987496431096,
                    "longitude": 106.79215325200744
                },
                {
                    "latitude": 10.797740738580886,
                    "longitude": 106.79215861642547
                },
                {
                    "latitude": 10.79737056025804,
                    "longitude": 106.792165321948
                },
                {
                    "latitude": 10.796218525512767,
                    "longitude": 106.79218141520215
                },
                {
                    "latitude": 10.79609115261789,
                    "longitude": 106.7921894618292
                },
                {
                    "latitude": 10.795935620936088,
                    "longitude": 106.79219214403821
                },
                {
                    "latitude": 10.795506405771356,
                    "longitude": 106.79220019066526
                },
                {
                    "latitude": 10.793426354365494,
                    "longitude": 106.79223908269597
                }
            ]
        },
        "@version": "traffic-service-flow 1.0.133"
    }
}